{
    "rounds":[
        {
            "standardImage": {
                "male":["gun"],
                "female":["gun"]
            },
            "locateImage": {
                "male": "silencerGun",
                "female": "silencerGun"
            },
            "locateFunction": "spritesheet",
            "params": {
                "male": "gunSprite",
                "female": "gunSprite"
            },
            "locateNum": 15,
            "particles": "bullet",
            "findText": "Guns with Silencers to Find: ",
            "hintText": {
                "male": "",
                "female": ""
            },
            "fTextX": 280,
            "hTextX": 250,
            "board": [
                  ["S", "S", "S", "L", "S", "S", "S", "S", "S", "S"],
                  ["S", "S", "L", "S", "S", "L", "S", "S", "S", "L"],
                  ["S", "S", "S", "S", "S", "S", "L", "S", "S", "S"],
                  ["S", "L", "S", "S", "S", "S", "S", "S", "S", "S"],
                  ["S", "S", "L", "S", "S", "S", "S", "S", "S", "S"],
                  ["S", "S", "S", "S", "L", "S", "S", "S", "L", "S"],
                  ["S", "L", "S", "S", "S", "S", "S", "L", "S", "S"],
                  ["S", "S", "L", "S", "S", "L", "S", "S", "S", "S"],
                  ["S", "S", "S", "L", "S", "S", "S", "S", "S", "S"],
                  ["L", "S", "S", "S", "S", "S", "S", "S", "S", "S"]
                ],
            "storyText": "Round up all of agent ____’s guns, __ has silencers on all of them so it should be easy to find them."
        },
        {
            "standardImage": {
                "male":["fingerprintR"],
                "female":["fingerprintR"]
            },
            "locateImage": {
                "male": "fingerprintL",
                "female": "fingerprintL"
            },
            "locateFunction": "rotate",
            "params": {
                "male": 1,
                "female": 1
            },
            "locateNum": 10,
            "particles": "bullet",
            "findText": "FingerPrints to Find: ",
            "hintText": {
                "male": "",
                "female": ""
            },
            "fTextX": 280,
            "hTextX": 250,
            "board": [
                  ["S", "S", "S", "S", "S", "S", "S", "S", "S", "S"],
                  ["S", "S", "L", "L", "S", "S", "S", "S", "S", "S"],
                  ["S", "S", "S", "S", "S", "S", "L", "S", "S", "S"],
                  ["S", "S", "S", "S", "S", "S", "S", "S", "S", "S"],
                  ["S", "S", "S", "S", "S", "S", "S", "S", "S", "S"],
                  ["S", "S", "S", "S", "L", "S", "S", "L", "L", "S"],
                  ["S", "L", "S", "S", "S", "S", "S", "S", "S", "S"],
                  ["S", "S", "S", "S", "S", "L", "S", "S", "S", "S"],
                  ["S", "S", "S", "S", "S", "S", "S", "S", "S", "S"],
                  ["L", "S", "S", "L", "S", "S", "S", "S", "S", "S"]
                ],
            "storyText": "Find - fingerprints to update our files."
        },
        {
            "standardImage": {
                "male":["folderLB", "folderLBL", "folderLBR", "folderLR", "folderLW"],
                "female":["folderMB", "folderMBL", "folderMBR", "folderMG", "folderMR", "folderMW"]
            },
            "locateImage": {
                "male": "folder",
                "female": "folder"
            },
            "locateFunction": "spritesheet",
            "params": {
                "male": "folderSpriteLady",
                "female": "folderSpriteMan"
            },
            "locateNum": 10,
            "particles": "bullet",
            "findText": "Folders to Update: ",
            "hintText": {
                "male": "The folders without Images of your Partner",
                "female": "The folders without Images  of your Partner"
            },
            "fTextX": 280,
            "hTextX": 250,
            "board": [
                  ["S", "S", "S", "S", "S", "S", "S", "S", "S", "S"],
                  ["S", "S", "L", "L", "S", "S", "S", "S", "S", "S"],
                  ["S", "S", "S", "S", "S", "S", "L", "S", "S", "S"],
                  ["S", "S", "S", "S", "S", "S", "S", "S", "S", "S"],
                  ["S", "S", "S", "S", "S", "S", "S", "S", "S", "S"],
                  ["S", "S", "S", "S", "L", "S", "S", "L", "L", "S"],
                  ["S", "L", "S", "S", "S", "S", "S", "S", "S", "S"],
                  ["S", "S", "S", "S", "S", "L", "S", "S", "S", "S"],
                  ["S", "S", "S", "S", "S", "S", "S", "S", "S", "S"],
                  ["L", "S", "S", "L", "S", "S", "S", "S", "S", "S"]
                ],
            "storyText": "Update Agent ____'s new files with all the information you collected."
        },
        {
            "standardImage": {
                "male":["usb"],
                "female":["usb"]
            },
            "locateImage": {
                "male": "usbYellow",
                "female": "usbYellow"
            },
            "locateFunction": "colour",
            "params": {
                "male": null,
                "female": null
            },
            "locateNum": 7,
            "particles": "bullet",
            "findText": "Compromised USBs to Find: ",
            "hintText": {
                "male": "",
                "female": ""
            },
            "fTextX": 280,
            "hTextX": 250,
            "board": [
                  ["S", "S", "L", "S", "S", "S", "S", "S", "S", "S"],
                  ["S", "S", "S", "S", "S", "S", "S", "S", "S", "L"],
                  ["S", "S", "S", "S", "S", "L", "S", "S", "S", "S"],
                  ["S", "S", "S", "S", "S", "S", "S", "S", "S", "S"],
                  ["L", "S", "S", "L", "S", "S", "S", "S", "S", "S"],
                  ["S", "S", "S", "S", "S", "S", "S", "S", "S", "S"],
                  ["S", "S", "S", "S", "S", "S", "S", "S", "L", "S"],
                  ["S", "S", "S", "S", "S", "S", "S", "L", "S", "S"],
                  ["S", "S", "S", "S", "S", "S", "S", "S", "S", "S"],
                  ["S", "S", "S", "S", "S", "S", "S", "S", "S", "S"]
                ],
            "storyText": "-- infected our digital files so you will need to locate all the infected usb drives we have."
        },
        {
            "standardImage": {
                "male":["passport"],
                "female":["passport"]
            },
            "locateImage": {
                "male": "passportBlack",
                "female": "passportBlack"
            },
            "locateFunction": "colour",
            "params": {
                "male": null,
                "female": null
            },
            "locateNum": 7,
            "particles": "bullet",
            "findText": "Passports to Find: ",
            "hintText": {
                "male": "",
                "female": ""
            },
            "fTextX": 280,
            "hTextX": 250,
            "board": [
                  ["S", "S", "S", "L", "S", "S", "S", "S", "S", "S"],
                  ["S", "S", "S", "S", "S", "S", "S", "S", "S", "S"],
                  ["S", "S", "S", "S", "S", "S", "L", "S", "S", "S"],
                  ["L", "L", "S", "S", "S", "S", "S", "S", "S", "S"],
                  ["S", "S", "S", "S", "S", "S", "S", "S", "S", "S"],
                  ["S", "S", "S", "S", "S", "l", "S", "S", "L", "S"],
                  ["S", "L", "S", "S", "S", "S", "S", "S", "S", "S"],
                  ["S", "S", "S", "S", "S", "S", "S", "S", "S", "S"],
                  ["S", "S", "l", "S", "S", "S", "S", "S", "S", "S"],
                  ["L", "S", "S", "S", "S", "S", "S", "S", "S", "S"]
                ],
            "storyText": "-- has several phony passports round up all the ones you can find to discover ___ alias."
        },
        {
            "standardImage": {
                "male": ["blondeF", "whiteF", "blackF", "redF"],
                "female": ["brownM", "whiteM", "blackM", "redM", "greyM"]
            },
            "locateImage": {
                "male": "brownF",
                "female": "blondM"
            },
            "locateFunction": "colour",
            "params": {
                "male": null,
                "female": null
            },
            "locateNum": 1,
            "particles": "bullet",
            "findText": "Double Agents to Find: ",
            "hintText": {
                "male": "(Hint: Enemy agents are Brunettes)",
                "female": "(Hint: Enemy agents are Blonds)"
            },
            "fTextX": 310,
            "hTextX": 250,
            "board": [
                  ["S", "S", "S", "S", "S", "S", "S", "S", "S", "S"],
                  ["S", "S", "S", "S", "S", "S", "S", "S", "S", "S"],
                  ["S", "S", "S", "S", "S", "S", "S", "S", "S", "S"],
                  ["S", "S", "S", "S", "S", "S", "S", "S", "S", "S"],
                  ["S", "S", "S", "S", "S", "S", "S", "S", "S", "S"],
                  ["S", "S", "S", "S", "S", "S", "S", "S", "S", "S"],
                  ["S", "S", "S", "S", "S", "S", "S", "S", "S", "S"],
                  ["S", "S", "S", "S", "S", "L", "S", "S", "S", "S"],
                  ["S", "S", "S", "S", "S", "S", "S", "S", "S", "S"],
                  ["S", "S", "S", "S", "S", "S", "S", "S", "S", "S"]
                ],
            "storyText": "Finally using all this information locate ___ and bring ___ in."
        }
    ],
    "StoryText":[
        "Hello Agent, I have some terrible news. Your partner agent ____, it turns out __ is a double agent. Agent we need you to find agent ____ and bring ___ in.  -- cleared our files of all information about ---- so we are at a complete loss without you. Our Intel tells us agent ____ was planning an assassination of an official overseas. In order to stop ___ you will need to do _ things:",
        "Can you do it Agent?"
    ],
    "nameM": "Man",
    "nameF": "Woman",
    "storySpecs":{
        "mainOffset": 90,
        "secondaryOffset": 95,
        "indentMain": "",
        "indentSecondary": "\t\t\t\t\t\t\t\t",
        "images": [
            {
                "line": 1,
                "word": 12,
                "x": 0,
                "y": 0,
                "image": "partners",
                "rotation": 6.5
            },
            {
                "line": 2,
                "word": 17,
                "x": 960,
                "y": 0,
                "image": "thief",
                "rotation": -6.5
            },
            {
                "line": 4,
                "word": 11,
                "x": 0,
                "y": 0,
                "image": "overseas",
                "rotation": 6.5
            },
            {
                "line": 8,
                "word": 8,
                "x": 0,
                "y": 0,
                "image": "gunImage",
                "rotation": 6.5
            },
            {
                "line": 11,
                "word": 4,
                "x": 960,
                "y": 0,
                "image": "fingerprintImage",
                "rotation": 0
            },
            {
                "line": 13,
                "word": 5,
                "x": 960,
                "y": 0,
                "image": "folderImage",
                "rotation": -6.5
            },
            {
                "line": 15,
                "word": 13,
                "x": 0,
                "y": 0,
                "image": "usbImage",
                "rotation": -6
            },
            {
                "line": 17,
                "word": 5,
                "x": 960,
                "y": 0,
                "image": "passportImage",
                "rotation": -6.5
            }
        ],
     "wordDelay": 200,
     "lineDelay": 500
    }
}